Steganopy/__init__.py
Steganopy/steganopy.py
idev_steganopy-1.4.1.dist-info/LICENSE
idev_steganopy-1.4.1.dist-info/METADATA
idev_steganopy-1.4.1.dist-info/WHEEL
idev_steganopy-1.4.1.dist-info/entry_points.txt
idev_steganopy-1.4.1.dist-info/top_level.txt
idev_steganopy-1.4.1.dist-info/RECORD
