Metadata-Version: 2.1
Name: idev-steganopy
Version: 1.4.1
Summary: A python script for hiding text into images (steganography).
Home-page: https://github.com/IrtsaDevelopment/Steganopy
Author: IrtsaDevelopment
Author-email: Irtsa <irtsa.development@gmail.com>
Project-URL: Homepage, https://github.com/IrtsaDevelopment/Steganopy
Project-URL: Bug Tracker, https://github.com/IrtsaDevelopment/Steganopy/issues
Classifier: Programming Language :: Python :: 3
Classifier: License :: OSI Approved :: MIT License
Classifier: Operating System :: OS Independent
Requires-Python: >=3.6
License-File: LICENSE
Requires-Dist: idev-pytermcolor
Requires-Dist: pillow
